voice_assistant/__init__.py
voice_assistant/core.py
voice_assistant/databases.py
voice_assistant-0.1.0.dist-info/METADATA
voice_assistant-0.1.0.dist-info/RECORD
voice_assistant-0.1.0.dist-info/WHEEL
voice_assistant-0.1.0.dist-info/top_level.txt
